ci/transparency/cwe/types/__init__.py
ci/transparency/cwe/types/py.typed
ci/transparency/cwe/types/base/__init__.py
ci/transparency/cwe/types/base/collections.py
ci/transparency/cwe/types/base/counts.py
ci/transparency/cwe/types/base/errors.py
ci/transparency/cwe/types/base/messages.py
ci/transparency/cwe/types/base/result_helpers.py
ci/transparency/cwe/types/base/schema.py
ci/transparency/cwe/types/cwe/__init__.py
ci/transparency/cwe/types/cwe/errors.py
ci/transparency/cwe/types/cwe/results.py
ci/transparency/cwe/types/cwe/schema/__init__.py
ci/transparency/cwe/types/cwe/schema/errors.py
ci/transparency/cwe/types/cwe/schema/results.py
ci/transparency/cwe/types/schema/__init__.py
ci/transparency/cwe/types/schema/errors.py
ci/transparency/cwe/types/schema/results.py
ci/transparency/cwe/types/schema_evolution/__init__.py
ci/transparency/cwe/types/schema_evolution/errors.py
ci/transparency/cwe/types/schema_evolution/results.py
ci/transparency/cwe/types/standards/__init__.py
ci/transparency/cwe/types/standards/errors.py
ci/transparency/cwe/types/standards/results.py
civic_transparency_cwe_types-0.0.12.dist-info/licenses/LICENSE
civic_transparency_cwe_types-0.0.12.dist-info/METADATA
civic_transparency_cwe_types-0.0.12.dist-info/WHEEL
civic_transparency_cwe_types-0.0.12.dist-info/top_level.txt
civic_transparency_cwe_types-0.0.12.dist-info/RECORD
