Metadata-Version: 2.4
Name: civic-transparency-cwe-types
Version: 0.0.12
Summary: Immutable datatype library for Common Weakness Enumeration (CWE) analysis and validation workflows
Author: Civic Interconnect
Project-URL: Bug Tracker, https://github.com/civic-interconnect/civic-transparency-py-cwe-types/issues
Project-URL: Documentation, https://civic-interconnect.github.io/civic-transparency-py-cwe-types/latest/
Project-URL: Homepage, https://github.com/civic-interconnect/civic-transparency-py-cwe-types
Project-URL: Repository, https://github.com/civic-interconnect/civic-transparency-py-cwe-types
Keywords: civic,transparency,cwe,security,vulnerability,dataclasses,types,validation
Classifier: Development Status :: 3 - Alpha
Classifier: Intended Audience :: Developers
Classifier: Intended Audience :: Science/Research
Classifier: Intended Audience :: Education
Classifier: Operating System :: OS Independent
Classifier: Programming Language :: Python :: 3
Classifier: Programming Language :: Python :: 3 :: Only
Classifier: Programming Language :: Python :: 3.12
Classifier: Programming Language :: Python :: 3.13
Classifier: Topic :: Security
Classifier: Topic :: Software Development :: Libraries :: Python Modules
Classifier: Topic :: Software Development :: Quality Assurance
Classifier: Typing :: Typed
Requires-Python: >=3.12
License-File: LICENSE
Provides-Extra: dev
Requires-Dist: bandit[toml]; extra == "dev"
Requires-Dist: build; extra == "dev"
Requires-Dist: deptry; extra == "dev"
Requires-Dist: pre-commit; extra == "dev"
Requires-Dist: pyright; extra == "dev"
Requires-Dist: pytest; extra == "dev"
Requires-Dist: pytest-cov; extra == "dev"
Requires-Dist: ruff; extra == "dev"
Requires-Dist: validate-pyproject; extra == "dev"
Provides-Extra: docs
Requires-Dist: mkdocs; extra == "docs"
Requires-Dist: mkdocs-gen-files; extra == "docs"
Requires-Dist: mkdocs-git-revision-date-localized-plugin; extra == "docs"
Requires-Dist: mkdocs-include-markdown-plugin; extra == "docs"
Requires-Dist: mkdocs-literate-nav; extra == "docs"
Requires-Dist: mkdocs-material; extra == "docs"
Requires-Dist: mkdocs-static-i18n; extra == "docs"
Requires-Dist: mkdocstrings[python]>=0.18; extra == "docs"
Requires-Dist: mike; extra == "docs"
Dynamic: license-file
